README.md
setup.cfg
setup.py
src/checkpoint_utils.egg-info/PKG-INFO
src/checkpoint_utils.egg-info/SOURCES.txt
src/checkpoint_utils.egg-info/dependency_links.txt
src/checkpoint_utils.egg-info/top_level.txt
src/checkpointer/__init__.py
src/checkpointer/checkpoint.py