Metadata-Version: 1.0
Name: checkpoint-utils
Version: 0.1.3
Summary: Checkpoint tool for working with unstable cloud services such as Google Colab or Kaggle Notebooks.
Home-page: https://github.com/gnom2134/checkpoint_utils
Author: Masalskiy Daniil
Author-email: gnom21345@gmail.com
License: MIT
Keywords: checkpoint colab kaggle parameters save
Platform: UNKNOWN
